{
  "fullName": "BREKKOTT CHAPMAN",
  "sourceUrl": "https://basketball.eurobasket.com/player/Brekkott-Chapman/333281",
  "height": "6'9'",
  "college": "University Games European Championships Olympic Games World Cup U17 European Championships U16\n\t\t    \n\t\t\t\n                \n\t\t\t\t\t\n                    \n                        \n                             BREKKOTT CHAPMAN basketball profile      Height",
  "currentTeam": "Tortona",
  "careerHistory": [
    {
      "year": "14-15",
      "team": "Utah",
      "league": "NCAA1"
    },
    {
      "year": "15-16",
      "team": "Utah",
      "league": "NCAA1"
    },
    {
      "year": "17-18",
      "team": "Weber St.",
      "league": "NCAA1"
    },
    {
      "year": "18-19",
      "team": "Weber St.",
      "league": "NCAA1"
    },
    {
      "year": "19-20",
      "team": "Wuerzburg",
      "league": "GER-1"
    },
    {
      "year": "20-21",
      "team": "Wuerzburg",
      "league": "GER-1"
    },
    {
      "year": "21-22",
      "team": "Heidelberg",
      "league": "GER-1"
    },
    {
      "year": "22-23",
      "team": "Koshigaya A.",
      "league": "JPN-2"
    },
    {
      "year": "23-24",
      "team": "Oldenburg",
      "league": "GER-20"
    },
    {
      "year": "23-24",
      "team": "Oldenburg",
      "league": "BCL-1"
    },
    {
      "year": "23-24",
      "team": "Oldenburg",
      "league": "GER-1"
    },
    {
      "year": "24-25",
      "team": "Kagawa FA",
      "league": "JPN-3"
    },
    {
      "year": "25-26",
      "team": "Tortona",
      "league": "ITA-1"
    }
  ],
  "_lastVerified": "2026-04-30T19:43:47.525Z",
  "_sources": [
    "eurobasket.com"
  ],
  "_dataConfidence": "high",
  "cachedAt": "2026-04-30T19:43:47.525Z"
}