{
  "fullName": "DANIIL SHELIST",
  "sourceUrl": "https://basketball.eurobasket.com/player/Daniil-Shelist/530174",
  "height": "6'9'",
  "currentTeam": "Oviedo",
  "careerHistory": [
    {
      "year": "19-20",
      "team": "Unicaja",
      "league": "ANGT-1"
    },
    {
      "year": "19-20",
      "team": "Unicaja-Andal.",
      "league": "ESP-4"
    },
    {
      "year": "20-21",
      "team": "Unicaja",
      "league": "ANGT-1"
    },
    {
      "year": "20-21",
      "team": "Unicaja-Andal.",
      "league": "ESP-4"
    },
    {
      "year": "20-21",
      "team": "Unicaja",
      "league": "ESP-5"
    },
    {
      "year": "21-22",
      "team": "Zentro Basket",
      "league": "ESP-3"
    },
    {
      "year": "21-22",
      "team": "Zentro Basket 2",
      "league": "ESP-4"
    },
    {
      "year": "22-23",
      "team": "Zentro Basket",
      "league": "ESP-4"
    },
    {
      "year": "23-24",
      "team": "ZA Enamora",
      "league": "ESP-3"
    },
    {
      "year": "24-25",
      "team": "Lobe Huesca LM",
      "league": "ESP-3"
    },
    {
      "year": "25-26",
      "team": "Oviedo",
      "league": "ESP-2"
    }
  ],
  "_lastVerified": "2026-04-30T21:49:11.789Z",
  "_sources": [
    "eurobasket.com"
  ],
  "_dataConfidence": "high",
  "cachedAt": "2026-04-30T21:49:11.789Z"
}