{
  "fullName": "GIAN CLAVELL",
  "sourceUrl": "https://basketball.eurobasket.com/player/Gian-Clavell/295534",
  "height": "6'4'",
  "currentTeam": "AEK",
  "careerHistory": [
    {
      "year": "13-14",
      "team": "Northwest Kansas Technical College",
      "league": "JUCO"
    },
    {
      "year": "14-15",
      "team": "Colorado St.",
      "league": "NCAA1"
    },
    {
      "year": "15-16",
      "team": "Colorado St.",
      "league": "NCAA1"
    },
    {
      "year": "16-17",
      "team": "Colorado St.",
      "league": "NCAA1"
    },
    {
      "year": "2017",
      "team": "Guayama",
      "league": "PUR-1"
    },
    {
      "year": "17-18",
      "team": "Texas L.",
      "league": "G League"
    },
    {
      "year": "17-18",
      "team": "Dallas M.",
      "league": "NBA"
    },
    {
      "year": "17-18",
      "team": "Sakarya",
      "league": "TUR-1"
    },
    {
      "year": "18-19",
      "team": "Estudiantes",
      "league": "ESP-1"
    },
    {
      "year": "2019",
      "team": "Portland TB",
      "league": "NBA"
    },
    {
      "year": "19-20",
      "team": "Bursaspor",
      "league": "TUR-1"
    },
    {
      "year": "19-20",
      "team": "Portland TB",
      "league": "NBA"
    },
    {
      "year": "20-21",
      "team": "Avtodor Saratov",
      "league": "VTB-1"
    },
    {
      "year": "20-21",
      "team": "Promitheas",
      "league": "GRE-1"
    },
    {
      "year": "21-22",
      "team": "Budivelnyk",
      "league": "UKR-1"
    },
    {
      "year": "2022",
      "team": "Santurce",
      "league": "PUR-1"
    },
    {
      "year": "22-23",
      "team": "Prometey",
      "league": "LAES-1"
    },
    {
      "year": "22-23",
      "team": "Prometey",
      "league": "Eurocup-1"
    },
    {
      "year": "2023",
      "team": "Santurce",
      "league": "PUR-1"
    },
    {
      "year": "23-24",
      "team": "Prometey",
      "league": "Eurocup-1"
    },
    {
      "year": "23-24",
      "team": "Prometey",
      "league": "LAES-1"
    },
    {
      "year": "2024",
      "team": "Quebradillas",
      "league": "PUR-1"
    },
    {
      "year": "24-25",
      "team": "Coviran Granada",
      "league": "ESP-1"
    },
    {
      "year": "2025",
      "team": "Quebradillas",
      "league": "PUR-1"
    },
    {
      "year": "25-26",
      "team": "Valcea",
      "league": "FEL-1"
    },
    {
      "year": "25-26",
      "team": "AEK",
      "league": "BCL-1"
    },
    {
      "year": "25-26",
      "team": "AEK",
      "league": "GRE-1"
    },
    {
      "year": "25-26",
      "team": "Valcea",
      "league": "ROM-1"
    }
  ],
  "_lastVerified": "2026-05-01T02:17:48.540Z",
  "_sources": [
    "eurobasket.com"
  ],
  "_dataConfidence": "high",
  "cachedAt": "2026-04-30T20:12:30.072Z",
  "birthdate": "November 26 1993",
  "birthCity": "Caguas"
}