{
  "fullName": "ISIAH SMALL",
  "sourceUrl": "https://basketball.eurobasket.com/player/Isiah-Small/504010",
  "height": "6'8'",
  "college": "University Games European Championships World Championships U21 European Championships U18 European Championships U16 Youth Olympic Games\n\t\t    \n\t\t\t\n                \n\t\t\t\t\t\n                    \n                        \n                             ISIAH SMALL basketball profile     Uniform",
  "currentTeam": "Kiryat Ata",
  "careerHistory": [
    {
      "year": "18-19",
      "team": "Seward County",
      "league": "JUCO"
    },
    {
      "year": "19-20",
      "team": "Texas St.",
      "league": "NCAA1"
    },
    {
      "year": "20-21",
      "team": "Texas St.",
      "league": "NCAA1"
    },
    {
      "year": "21-22",
      "team": "Texas St.",
      "league": "NCAA1"
    },
    {
      "year": "2022",
      "team": "Z*B1 Ballers",
      "league": "TBT"
    },
    {
      "year": "22-23",
      "team": "Bernau",
      "league": "GER-3"
    },
    {
      "year": "23-24",
      "team": "Akhaltsikhe",
      "league": "GEO-1"
    },
    {
      "year": "24-25",
      "team": "Svendborg",
      "league": "DEN-1"
    },
    {
      "year": "25-26",
      "team": "Surrey",
      "league": "ENG-20"
    },
    {
      "year": "25-26",
      "team": "Surrey",
      "league": "ENG-1"
    },
    {
      "year": "25-26",
      "team": "Kiryat Ata",
      "league": "ISR-1"
    }
  ],
  "_lastVerified": "2026-05-01T02:23:40.889Z",
  "_sources": [
    "eurobasket.com"
  ],
  "_dataConfidence": "high",
  "cachedAt": "2026-04-30T20:36:01.382Z",
  "nationality": "USA",
  "birthdate": "September 15 1998",
  "birthCity": "Jersey City"
}