{
  "fullName": "JEREMY ROACH",
  "sourceUrl": "https://basketball.eurobasket.com/player/Jeremy-Roach/422512",
  "height": "6'2'",
  "college": "University and his sister Chloe played at Eastern Mennonite University\nYear",
  "currentTeam": "King",
  "careerHistory": [
    {
      "year": "20-21",
      "team": "Duke",
      "league": "NCAA1"
    },
    {
      "year": "21-22",
      "team": "Duke",
      "league": "NCAA1"
    },
    {
      "year": "22-23",
      "team": "Duke",
      "league": "NCAA1"
    },
    {
      "year": "23-24",
      "team": "Duke",
      "league": "NCAA1"
    },
    {
      "year": "24-25",
      "team": "Baylor",
      "league": "NCAA1"
    },
    {
      "year": "25-26",
      "team": "King",
      "league": "POL-1"
    }
  ],
  "_lastVerified": "2026-04-30T20:39:27.971Z",
  "_sources": [
    "eurobasket.com"
  ],
  "_dataConfidence": "high",
  "cachedAt": "2026-04-30T20:39:27.971Z"
}