{
  "fullName": "JOSH JEFFERSON",
  "sourceUrl": "https://basketball.eurobasket.com/player/Josh-Jefferson/416193",
  "height": "6'2'",
  "college": "University of Wisconsin",
  "currentTeam": "Nevezis",
  "careerHistory": [
    {
      "year": "16-17",
      "team": "Lake Land",
      "league": "JUCO"
    },
    {
      "year": "17-18",
      "team": "Lake Land",
      "league": "JUCO"
    },
    {
      "year": "18-19",
      "team": "Illinois St.",
      "league": "NCAA2"
    },
    {
      "year": "18-19",
      "team": "Illinois St.",
      "league": "NCAA1"
    },
    {
      "year": "20-21",
      "team": "Green Bay",
      "league": "NCAA1"
    },
    {
      "year": "21-22",
      "team": "MTSU",
      "league": "NCAA1"
    },
    {
      "year": "22-23",
      "team": "Surrey",
      "league": "ENG-1"
    },
    {
      "year": "22-23",
      "team": "Kumanovo",
      "league": "MKD-1"
    },
    {
      "year": "23-24",
      "team": "Valur",
      "league": "ISL-1"
    },
    {
      "year": "24-25",
      "team": "Valur",
      "league": "ISL-1"
    },
    {
      "year": "25-26",
      "team": "Spisski Rytieri",
      "league": "SVK-1"
    },
    {
      "year": "25-26",
      "team": "Nevezis",
      "league": "LTU-1"
    }
  ],
  "_lastVerified": "2026-04-30T20:55:46.091Z",
  "_sources": [
    "eurobasket.com"
  ],
  "_dataConfidence": "high",
  "cachedAt": "2026-04-30T20:55:46.091Z"
}