{
  "fullName": "KYLE RIDDLEY",
  "sourceUrl": "https://basketball.eurobasket.com/player/Kyle-Riddley/357305",
  "height": "6'4'",
  "currentTeam": "Nantes",
  "careerHistory": [
    {
      "year": "14-15",
      "team": "Davidson-Davie",
      "league": "JUCO"
    },
    {
      "year": "15-16",
      "team": "Davidson-Davie",
      "league": "JUCO"
    },
    {
      "year": "17-18",
      "team": "Greensboro",
      "league": "NCAA1"
    },
    {
      "year": "17-18",
      "team": "Greensboro",
      "league": "NCAA3"
    },
    {
      "year": "18-19",
      "team": "Pfeiffer",
      "league": "NCAA1"
    },
    {
      "year": "18-19",
      "team": "Pfeiffer",
      "league": "NCAA2"
    },
    {
      "year": "18-19",
      "team": "Pfeiffer",
      "league": "NCAA3"
    },
    {
      "year": "19-20",
      "team": "Tallinna Kalev",
      "league": "EST-1"
    },
    {
      "year": "21-22",
      "team": "Batumi",
      "league": "GEO-1"
    },
    {
      "year": "22-23",
      "team": "Batumi",
      "league": "GEO-1"
    },
    {
      "year": "2023",
      "team": "Z*Georgia K.",
      "league": "TBT"
    },
    {
      "year": "23-24",
      "team": "OSE Lions",
      "league": "HUN-1"
    },
    {
      "year": "2024",
      "team": "Sweet Home Alabama",
      "league": "TBT"
    },
    {
      "year": "24-25",
      "team": "Nantes",
      "league": "FRA-2"
    },
    {
      "year": "25-26",
      "team": "Nantes",
      "league": "FRA-2"
    }
  ],
  "_lastVerified": "2026-04-30T21:26:03.495Z",
  "_sources": [
    "eurobasket.com"
  ],
  "_dataConfidence": "high",
  "cachedAt": "2026-04-30T21:26:03.495Z"
}