{
  "fullName": "Matt Coleman III",
  "birthdate": "January 22, 1998",
  "birthCity": "Norfolk, VA",
  "height": "6'2\"",
  "heightCm": "188",
  "weight": "180",
  "weightKg": "82",
  "position": "Point guard",
  "nationality": "USA",
  "college": "Texas",
  "highSchool": "Oak Hill Acad. (VA)",
  "currentTeam": "Enisey",
  "currentLeague": "VTB-1",
  "careerHistory": [
    {
      "year": "17-18",
      "team": "Texas",
      "league": "NCAA1"
    },
    {
      "year": "18-19",
      "team": "Texas",
      "league": "NCAA1"
    },
    {
      "year": "19-20",
      "team": "Texas",
      "league": "NCAA1"
    },
    {
      "year": "20-21",
      "team": "Texas",
      "league": "NCAA1"
    },
    {
      "year": "2021",
      "team": "Sacramento K.",
      "league": "NBA"
    },
    {
      "year": "2021",
      "team": "Sacramento K.",
      "league": "NBA"
    },
    {
      "year": "21-22",
      "team": "Stockton",
      "league": "G League"
    },
    {
      "year": "2022",
      "team": "Sacramento K.",
      "league": "NBA"
    },
    {
      "year": "2022",
      "team": "Sacramento K.",
      "league": "NBA"
    },
    {
      "year": "22-23",
      "team": "Besiktas",
      "league": "FEL-1"
    },
    {
      "year": "22-23",
      "team": "Konyaspor",
      "league": "TUR-1"
    },
    {
      "year": "22-23",
      "team": "Besiktas",
      "league": "TUR-1"
    },
    {
      "year": "22-23",
      "team": "Peristeri",
      "league": "GRE-1"
    },
    {
      "year": "2023",
      "team": "Ottawa",
      "league": "CEBL"
    },
    {
      "year": "23-24",
      "team": "Dziki",
      "league": "POL-1"
    },
    {
      "year": "24-25",
      "team": "Hapoel Haifa",
      "league": "ISR-1"
    },
    {
      "year": "2025",
      "team": "Ottawa",
      "league": "CEBL"
    },
    {
      "year": "25-26",
      "team": "Enisey",
      "league": "VTB-1"
    }
  ],
  "seasonStats": [
    {
      "year": "17-18",
      "team": "Texas",
      "league": "NCAA1",
      "gamesPlayed": 34,
      "minutes": 1157,
      "ppg": 10.2,
      "rpg": 2.5,
      "apg": 4.1,
      "spg": 1.2,
      "bpg": 0,
      "fgPct": 0.471,
      "threePct": 0.286,
      "ftPct": 0.787,
      "totalPoints": 346,
      "totalRebounds": 85,
      "totalAssists": 140,
      "totalSteals": 40,
      "totalBlocks": 1,
      "twoFgMade": 96,
      "twoFgAttempted": 204,
      "threeFgMade": 28,
      "threeFgAttempted": 98,
      "ftMade": 70,
      "ftAttempted": 89,
      "offRebounds": 24,
      "defRebounds": 61,
      "personalFouls": 103,
      "turnovers": 74,
      "isCollegiate": true
    },
    {
      "year": "18-19",
      "team": "Texas",
      "league": "NCAA1",
      "gamesPlayed": 37,
      "minutes": 1104,
      "ppg": 9.8,
      "rpg": 2.1,
      "apg": 3.4,
      "spg": 0.8,
      "bpg": 0.1,
      "fgPct": 0.431,
      "threePct": 0.326,
      "ftPct": 0.785,
      "totalPoints": 364,
      "totalRebounds": 79,
      "totalAssists": 126,
      "totalSteals": 30,
      "totalBlocks": 3,
      "twoFgMade": 81,
      "twoFgAttempted": 188,
      "threeFgMade": 43,
      "threeFgAttempted": 132,
      "ftMade": 73,
      "ftAttempted": 93,
      "offRebounds": 17,
      "defRebounds": 62,
      "personalFouls": 96,
      "turnovers": 63,
      "isCollegiate": true
    },
    {
      "year": "19-20",
      "team": "Texas",
      "league": "NCAA1",
      "gamesPlayed": 29,
      "minutes": 975,
      "ppg": 12.7,
      "rpg": 3.1,
      "apg": 3.3,
      "spg": 1.3,
      "bpg": 0.1,
      "fgPct": 0.466,
      "threePct": 0.407,
      "ftPct": 0.8,
      "totalPoints": 368,
      "totalRebounds": 89,
      "totalAssists": 96,
      "totalSteals": 39,
      "totalBlocks": 2,
      "twoFgMade": 90,
      "twoFgAttempted": 193,
      "threeFgMade": 44,
      "threeFgAttempted": 108,
      "ftMade": 56,
      "ftAttempted": 70,
      "offRebounds": 22,
      "defRebounds": 67,
      "personalFouls": 62,
      "turnovers": 69,
      "isCollegiate": true
    },
    {
      "year": "20-21",
      "team": "Texas",
      "league": "NCAA1",
      "gamesPlayed": 27,
      "minutes": 906,
      "ppg": 13.2,
      "rpg": 3.5,
      "apg": 4,
      "spg": 1.2,
      "bpg": 0.1,
      "fgPct": 0.568,
      "threePct": 0.377,
      "ftPct": 0.813,
      "totalPoints": 356,
      "totalRebounds": 94,
      "totalAssists": 109,
      "totalSteals": 32,
      "totalBlocks": 2,
      "twoFgMade": 83,
      "twoFgAttempted": 146,
      "threeFgMade": 43,
      "threeFgAttempted": 114,
      "ftMade": 61,
      "ftAttempted": 75,
      "offRebounds": 19,
      "defRebounds": 75,
      "personalFouls": 59,
      "turnovers": 70,
      "isCollegiate": true
    },
    {
      "year": "2021",
      "team": "Sacramento K.",
      "league": "NBA",
      "gamesPlayed": 3,
      "minutes": 38,
      "ppg": 4,
      "rpg": 0.3,
      "apg": 1.7,
      "spg": 1.7,
      "bpg": 0,
      "fgPct": 0.444,
      "threePct": 0.167,
      "ftPct": 1,
      "totalPoints": 12,
      "totalRebounds": 1,
      "totalAssists": 5,
      "totalSteals": 5,
      "totalBlocks": 0,
      "twoFgMade": 4,
      "twoFgAttempted": 9,
      "threeFgMade": 1,
      "threeFgAttempted": 6,
      "ftMade": 1,
      "ftAttempted": 1,
      "offRebounds": 0,
      "defRebounds": 1,
      "personalFouls": 4,
      "turnovers": 4,
      "isCollegiate": false
    },
    {
      "year": "2021",
      "team": "Sacramento K.",
      "league": "NBA",
      "gamesPlayed": 3,
      "minutes": 54,
      "ppg": 11.7,
      "rpg": 1.3,
      "apg": 3,
      "spg": 0.7,
      "bpg": 0,
      "fgPct": 0.688,
      "threePct": 0.5,
      "ftPct": 1,
      "totalPoints": 35,
      "totalRebounds": 4,
      "totalAssists": 9,
      "totalSteals": 2,
      "totalBlocks": 0,
      "twoFgMade": 11,
      "twoFgAttempted": 16,
      "threeFgMade": 4,
      "threeFgAttempted": 8,
      "ftMade": 1,
      "ftAttempted": 1,
      "offRebounds": 0,
      "defRebounds": 4,
      "personalFouls": 5,
      "turnovers": 2,
      "isCollegiate": false
    },
    {
      "year": "21-22",
      "team": "Stockton",
      "league": "G League",
      "gamesPlayed": 48,
      "minutes": 1484,
      "ppg": 13.1,
      "rpg": 3.7,
      "apg": 5.3,
      "spg": 1.4,
      "bpg": 0.1,
      "fgPct": 0.503,
      "threePct": 0.344,
      "ftPct": 0.781,
      "totalPoints": 630,
      "totalRebounds": 176,
      "totalAssists": 252,
      "totalSteals": 68,
      "totalBlocks": 7,
      "twoFgMade": 192,
      "twoFgAttempted": 382,
      "threeFgMade": 54,
      "threeFgAttempted": 157,
      "ftMade": 57,
      "ftAttempted": 73,
      "offRebounds": 45,
      "defRebounds": 131,
      "personalFouls": 109,
      "turnovers": 104,
      "isCollegiate": false
    },
    {
      "year": "2022",
      "team": "Sacramento K.",
      "league": "NBA",
      "gamesPlayed": 5,
      "minutes": 77,
      "ppg": 6.6,
      "rpg": 1.2,
      "apg": 3.2,
      "spg": 0.8,
      "bpg": 0.2,
      "fgPct": 0.522,
      "threePct": 0.25,
      "ftPct": 0.667,
      "totalPoints": 33,
      "totalRebounds": 6,
      "totalAssists": 16,
      "totalSteals": 4,
      "totalBlocks": 1,
      "twoFgMade": 12,
      "twoFgAttempted": 23,
      "threeFgMade": 1,
      "threeFgAttempted": 4,
      "ftMade": 6,
      "ftAttempted": 9,
      "offRebounds": 3,
      "defRebounds": 3,
      "personalFouls": 9,
      "turnovers": 7,
      "isCollegiate": false
    },
    {
      "year": "2022",
      "team": "Sacramento K.",
      "league": "NBA",
      "gamesPlayed": 4,
      "minutes": 62,
      "ppg": 5,
      "rpg": 1.8,
      "apg": 2,
      "spg": 0.3,
      "bpg": 0,
      "fgPct": 0.455,
      "threePct": 0.286,
      "ftPct": 0.667,
      "totalPoints": 20,
      "totalRebounds": 7,
      "totalAssists": 8,
      "totalSteals": 1,
      "totalBlocks": 0,
      "twoFgMade": 5,
      "twoFgAttempted": 11,
      "threeFgMade": 2,
      "threeFgAttempted": 7,
      "ftMade": 4,
      "ftAttempted": 6,
      "offRebounds": 1,
      "defRebounds": 6,
      "personalFouls": 9,
      "turnovers": 6,
      "isCollegiate": false
    },
    {
      "year": "22-23",
      "team": "Besiktas",
      "league": "FEL-1",
      "gamesPlayed": 1,
      "minutes": 29,
      "ppg": 3,
      "rpg": 5,
      "apg": 7,
      "spg": 2,
      "bpg": 0,
      "fgPct": 0.5,
      "threePct": 0,
      "ftPct": 0.5,
      "totalPoints": 3,
      "totalRebounds": 5,
      "totalAssists": 7,
      "totalSteals": 2,
      "totalBlocks": 0,
      "twoFgMade": 1,
      "twoFgAttempted": 2,
      "threeFgMade": 0,
      "threeFgAttempted": 2,
      "ftMade": 1,
      "ftAttempted": 2,
      "offRebounds": 2,
      "defRebounds": 3,
      "personalFouls": 4,
      "turnovers": 1,
      "isCollegiate": false
    },
    {
      "year": "22-23",
      "team": "Konyaspor",
      "league": "TUR-1",
      "gamesPlayed": 6,
      "minutes": 124,
      "ppg": 6.3,
      "rpg": 2.5,
      "apg": 3,
      "spg": 1.2,
      "bpg": 0.2,
      "fgPct": 0.429,
      "threePct": 0.235,
      "ftPct": 1,
      "totalPoints": 38,
      "totalRebounds": 15,
      "totalAssists": 18,
      "totalSteals": 7,
      "totalBlocks": 1,
      "twoFgMade": 9,
      "twoFgAttempted": 21,
      "threeFgMade": 4,
      "threeFgAttempted": 17,
      "ftMade": 8,
      "ftAttempted": 8,
      "offRebounds": 5,
      "defRebounds": 10,
      "personalFouls": 10,
      "turnovers": 12,
      "isCollegiate": false
    },
    {
      "year": "22-23",
      "team": "Besiktas",
      "league": "TUR-1",
      "gamesPlayed": 6,
      "minutes": 176,
      "ppg": 10,
      "rpg": 2.3,
      "apg": 2.7,
      "spg": 0.7,
      "bpg": 0.2,
      "fgPct": 0.609,
      "threePct": 0.45,
      "ftPct": 0.833,
      "totalPoints": 60,
      "totalRebounds": 14,
      "totalAssists": 16,
      "totalSteals": 4,
      "totalBlocks": 1,
      "twoFgMade": 14,
      "twoFgAttempted": 23,
      "threeFgMade": 9,
      "threeFgAttempted": 20,
      "ftMade": 5,
      "ftAttempted": 6,
      "offRebounds": 0,
      "defRebounds": 14,
      "personalFouls": 15,
      "turnovers": 13,
      "isCollegiate": false
    },
    {
      "year": "22-23",
      "team": "Peristeri",
      "league": "GRE-1",
      "gamesPlayed": 17,
      "minutes": 218,
      "ppg": 3.4,
      "rpg": 1.4,
      "apg": 0.9,
      "spg": 0.8,
      "bpg": 0,
      "fgPct": 0.452,
      "threePct": 0.24,
      "ftPct": 0.857,
      "totalPoints": 58,
      "totalRebounds": 24,
      "totalAssists": 16,
      "totalSteals": 14,
      "totalBlocks": 0,
      "twoFgMade": 14,
      "twoFgAttempted": 31,
      "threeFgMade": 6,
      "threeFgAttempted": 25,
      "ftMade": 12,
      "ftAttempted": 14,
      "offRebounds": 8,
      "defRebounds": 16,
      "personalFouls": 38,
      "turnovers": 13,
      "isCollegiate": false
    },
    {
      "year": "2023",
      "team": "Ottawa",
      "league": "CEBL",
      "gamesPlayed": 9,
      "minutes": 248,
      "ppg": 9.4,
      "rpg": 3.9,
      "apg": 4.1,
      "spg": 1.7,
      "bpg": 0,
      "fgPct": 0.444,
      "threePct": 0.273,
      "ftPct": 0.846,
      "totalPoints": 85,
      "totalRebounds": 35,
      "totalAssists": 37,
      "totalSteals": 15,
      "totalBlocks": 0,
      "twoFgMade": 28,
      "twoFgAttempted": 63,
      "threeFgMade": 6,
      "threeFgAttempted": 22,
      "ftMade": 11,
      "ftAttempted": 13,
      "offRebounds": 10,
      "defRebounds": 25,
      "personalFouls": 24,
      "turnovers": 20,
      "isCollegiate": false
    },
    {
      "year": "23-24",
      "team": "Dziki",
      "league": "POL-1",
      "gamesPlayed": 30,
      "minutes": 806,
      "ppg": 12.1,
      "rpg": 3.2,
      "apg": 3.6,
      "spg": 1.3,
      "bpg": 0,
      "fgPct": 0.51,
      "threePct": 0.365,
      "ftPct": 0.773,
      "totalPoints": 364,
      "totalRebounds": 95,
      "totalAssists": 107,
      "totalSteals": 38,
      "totalBlocks": 1,
      "twoFgMade": 104,
      "twoFgAttempted": 204,
      "threeFgMade": 35,
      "threeFgAttempted": 96,
      "ftMade": 51,
      "ftAttempted": 66,
      "offRebounds": 24,
      "defRebounds": 71,
      "personalFouls": 88,
      "turnovers": 68,
      "isCollegiate": false
    },
    {
      "year": "24-25",
      "team": "Hapoel Haifa",
      "league": "ISR-1",
      "gamesPlayed": 22,
      "minutes": 612,
      "ppg": 14.9,
      "rpg": 2.7,
      "apg": 5.7,
      "spg": 1.6,
      "bpg": 0.1,
      "fgPct": 0.475,
      "threePct": 0.425,
      "ftPct": 0.786,
      "totalPoints": 327,
      "totalRebounds": 59,
      "totalAssists": 126,
      "totalSteals": 35,
      "totalBlocks": 2,
      "twoFgMade": 86,
      "twoFgAttempted": 181,
      "threeFgMade": 37,
      "threeFgAttempted": 87,
      "ftMade": 44,
      "ftAttempted": 56,
      "offRebounds": 17,
      "defRebounds": 42,
      "personalFouls": 71,
      "turnovers": 66,
      "isCollegiate": false
    },
    {
      "year": "2025",
      "team": "Ottawa",
      "league": "CEBL",
      "gamesPlayed": 7,
      "minutes": 180,
      "ppg": 9.9,
      "rpg": 2.7,
      "apg": 5.4,
      "spg": 0.6,
      "bpg": 0,
      "fgPct": 0.545,
      "threePct": 0.2,
      "ftPct": 0.857,
      "totalPoints": 69,
      "totalRebounds": 19,
      "totalAssists": 38,
      "totalSteals": 4,
      "totalBlocks": 0,
      "twoFgMade": 24,
      "twoFgAttempted": 44,
      "threeFgMade": 3,
      "threeFgAttempted": 15,
      "ftMade": 12,
      "ftAttempted": 14,
      "offRebounds": 4,
      "defRebounds": 15,
      "personalFouls": 18,
      "turnovers": 16,
      "isCollegiate": false
    },
    {
      "year": "25-26",
      "team": "Enisey",
      "league": "VTB-1",
      "gamesPlayed": 38,
      "minutes": 1110,
      "ppg": 10.7,
      "rpg": 2.7,
      "apg": 5.1,
      "spg": 1.1,
      "bpg": 0,
      "fgPct": 0.48,
      "threePct": 0.349,
      "ftPct": 0.838,
      "totalPoints": 407,
      "totalRebounds": 101,
      "totalAssists": 194,
      "totalSteals": 43,
      "totalBlocks": 1,
      "twoFgMade": 109,
      "twoFgAttempted": 227,
      "threeFgMade": 44,
      "threeFgAttempted": 126,
      "ftMade": 57,
      "ftAttempted": 68,
      "offRebounds": 23,
      "defRebounds": 78,
      "personalFouls": 120,
      "turnovers": 87,
      "isCollegiate": false,
      "highlights": [
        "Had 23 points on 8-for-10 shooting as well as 4 assists and 4-for-6 from three in 32 minutes November 1 vs. Zenit",
        "Had 19 points on 8-for-12 shooting as well as 6 rebounds and 4 assists in 29 minutes March 14 vs. Zenit",
        "Dropped 17 points on 6-for-13 shooting as well as 9 assists and 2 steals in 36 minutes March 8 vs. Lokomotiv",
        "Put up 14 points on 6-for-15 shooting as well as 7 rebounds, 9 assists and 2 steals in 42 minutes October 25 vs. Uralmash",
        "Put up 18 points on 6-for-11 shooting as well as 7 rebounds, 4 assists and 3-for-5 from three in 33 minutes November 23 vs. Avtodor"
      ]
    }
  ],
  "personalInfo": [],
  "sources": [
    "https://basketball.eurobasket.com/player/Matt-Coleman-III/337670"
  ],
  "cachedAt": "2026-04-17T20:57:06.998Z",
  "_lastVerified": "2026-04-17T20:57:06.998Z",
  "_sources": [
    "https://basketball.eurobasket.com/player/Matt-Coleman-III/337670"
  ],
  "_dataConfidence": "high"
}