{
  "fullName": "MICHELE RUZZIER",
  "sourceUrl": "https://basketball.eurobasket.com/player/Michele-Ruzzier/215664",
  "height": "6'0'",
  "college": "University Games European Championships Olympic Games World Cup U17 European Championships U16\n\t\t    \n\t\t\t\n                \n\t\t\t\t\t\n                    \n                        \n                             MICHELE RUZZIER basketball profile     Height",
  "currentTeam": "Trieste",
  "careerHistory": [
    {
      "year": "10-11",
      "team": "AcegasAps TR",
      "league": "ITA-3"
    },
    {
      "year": "11-12",
      "team": "AcegasAps TR",
      "league": "ITA-3"
    },
    {
      "year": "12-13",
      "team": "AcegasAps TR",
      "league": "ITA-2"
    },
    {
      "year": "13-14",
      "team": "Pall.Trieste",
      "league": "ITA-2"
    },
    {
      "year": "14-15",
      "team": "Umana Reyer",
      "league": "ITA-1"
    },
    {
      "year": "15-16",
      "team": "Umana Reyer",
      "league": "Eurocup-1"
    },
    {
      "year": "15-16",
      "team": "Umana Reyer",
      "league": "ITA-1"
    },
    {
      "year": "16-17",
      "team": "Fortituto Kont.",
      "league": "ITA-2"
    },
    {
      "year": "17-18",
      "team": "Vanoli Cremona",
      "league": "ITA-1"
    },
    {
      "year": "18-19",
      "team": "Vanoli Cremona",
      "league": "ITA-1"
    },
    {
      "year": "19-20",
      "team": "Vanoli Cremona",
      "league": "ITA-1"
    },
    {
      "year": "2020",
      "team": "OpenjobMetis",
      "league": "ITA-20"
    },
    {
      "year": "20-21",
      "team": "OpenjobMetis",
      "league": "ITA-1"
    },
    {
      "year": "21-22",
      "team": "Virtus Segafredo",
      "league": "ITA-20"
    },
    {
      "year": "21-22",
      "team": "Virtus Segafredo",
      "league": "Eurocup-1"
    },
    {
      "year": "21-22",
      "team": "Virtus Segafredo",
      "league": "ITA-1"
    },
    {
      "year": "22-23",
      "team": "Trieste",
      "league": "ITA-1"
    },
    {
      "year": "22-23",
      "team": "Virtus Segafredo",
      "league": "ITA-1"
    },
    {
      "year": "23-24",
      "team": "Trieste",
      "league": "ITA-2"
    },
    {
      "year": "24-25",
      "team": "Trieste",
      "league": "ITA-1"
    },
    {
      "year": "25-26",
      "team": "Trieste",
      "league": "BCL-1"
    },
    {
      "year": "25-26",
      "team": "Trieste",
      "league": "ITA-1"
    }
  ],
  "_lastVerified": "2026-05-01T02:56:46.810Z",
  "_sources": [
    "eurobasket.com"
  ],
  "_dataConfidence": "high",
  "cachedAt": "2026-04-30T19:45:09.548Z",
  "nationality": "Italian",
  "birthdate": "February 9 1993",
  "birthCity": "Trieste"
}