{
  "fullName": "NAZARETH MITROU-LONG",
  "sourceUrl": "https://basketball.eurobasket.com/player/Nazareth-Mitrou-Long/262245",
  "height": "6'4'",
  "college": "University Games European Championships Olympic Games World Cup U17 European Championships U16\n\t\t    \n\t\t\t\n                \n\t\t\t\t\t\n                    \n                        \n                             NAZARETH MITROU",
  "currentTeam": "Napoli",
  "careerHistory": [
    {
      "year": "12-13",
      "team": "Iowa St.",
      "league": "NCAA1"
    },
    {
      "year": "13-14",
      "team": "Iowa St.",
      "league": "NCAA1"
    },
    {
      "year": "14-15",
      "team": "Iowa St.",
      "league": "NCAA1"
    },
    {
      "year": "15-16",
      "team": "Iowa St.",
      "league": "NCAA1"
    },
    {
      "year": "16-17",
      "team": "Iowa St.",
      "league": "NCAA1"
    },
    {
      "year": "17-18",
      "team": "SLC Stars",
      "league": "G League"
    },
    {
      "year": "17-18",
      "team": "Utah Jazz",
      "league": "NBA"
    },
    {
      "year": "18-19",
      "team": "Utah Jazz",
      "league": "NBA"
    },
    {
      "year": "18-19",
      "team": "SLC Stars",
      "league": "G League"
    },
    {
      "year": "2019",
      "team": "Cleveland C.",
      "league": "NBA"
    },
    {
      "year": "19-20",
      "team": "Fort Wayne MA",
      "league": "G League"
    },
    {
      "year": "19-20",
      "team": "Indiana Pacers",
      "league": "NBA"
    },
    {
      "year": "19-20",
      "team": "Cleveland C.",
      "league": "NBA"
    },
    {
      "year": "20-21",
      "team": "Fort Wayne MA",
      "league": "G League"
    },
    {
      "year": "21-22",
      "team": "Germani BR",
      "league": "ITA-20"
    },
    {
      "year": "21-22",
      "team": "Germani BR",
      "league": "ITA-1"
    },
    {
      "year": "22-23",
      "team": "AX Armani MI",
      "league": "EUROL-1"
    },
    {
      "year": "22-23",
      "team": "AX Armani MI",
      "league": "ITA-1"
    },
    {
      "year": "23-24",
      "team": "Zalgiris",
      "league": "EUROL-1"
    },
    {
      "year": "23-24",
      "team": "Olympiacos",
      "league": "EUROL-1"
    },
    {
      "year": "23-24",
      "team": "Zalgiris",
      "league": "LTU-1"
    },
    {
      "year": "23-24",
      "team": "Olympiacos",
      "league": "GRE-1"
    },
    {
      "year": "24-25",
      "team": "Olympiacos",
      "league": "EUROL-1"
    },
    {
      "year": "24-25",
      "team": "Olympiacos",
      "league": "GRE-1"
    },
    {
      "year": "25-26",
      "team": "Napoli",
      "league": "ITA-1"
    }
  ],
  "_lastVerified": "2026-05-01T03:00:46.700Z",
  "_sources": [
    "eurobasket.com"
  ],
  "_dataConfidence": "high",
  "cachedAt": "2026-04-30T19:46:56.728Z",
  "birthdate": "August 3 1993",
  "birthCity": "Mississauga",
  "nationality": "Canadian",
  "_inferredNationality": true
}