{
  "fullName": "RJ GUNN",
  "sourceUrl": "https://basketball.eurobasket.com/player/RJ-Gunn/453656",
  "height": "6'7'",
  "college": "University Games European Championships Olympic Games European Championships U16\n\t\t    \n\t\t\t\n                \n\t\t\t\t\t\n                    \n                        \n                             RJ GUNN basketball profile      Height",
  "currentTeam": "Weissenfels",
  "careerHistory": [
    {
      "year": "17-18",
      "team": "Lenoir-Rhyne",
      "league": "NCAA2"
    },
    {
      "year": "18-19",
      "team": "Lenoir-Rhyne",
      "league": "NCAA1"
    },
    {
      "year": "18-19",
      "team": "Lenoir-Rhyne",
      "league": "NCAA2"
    },
    {
      "year": "19-20",
      "team": "Lenoir-Rhyne",
      "league": "NCAA2"
    },
    {
      "year": "20-21",
      "team": "Lenoir-Rhyne",
      "league": "NCAA2"
    },
    {
      "year": "21-22",
      "team": "Duquesne",
      "league": "NCAA1"
    },
    {
      "year": "22-23",
      "team": "Duquesne",
      "league": "NCAA1"
    },
    {
      "year": "23-24",
      "team": "Leeuwarden",
      "league": "BNXT-1"
    },
    {
      "year": "23-24",
      "team": "Leeuwarden",
      "league": "NED-1"
    },
    {
      "year": "2024",
      "team": "Corsarios",
      "league": "COL-1"
    },
    {
      "year": "24-25",
      "team": "Inter Bratislava",
      "league": "SVK-1"
    },
    {
      "year": "24-25",
      "team": "Inter Bratislava",
      "league": "ENBL-1"
    },
    {
      "year": "25-26",
      "team": "Weissenfels",
      "league": "GER-20"
    },
    {
      "year": "25-26",
      "team": "Weissenfels",
      "league": "ENBL-1"
    },
    {
      "year": "25-26",
      "team": "Weissenfels",
      "league": "GER-1"
    }
  ],
  "_lastVerified": "2026-04-30T19:28:14.317Z",
  "_sources": [
    "eurobasket.com"
  ],
  "_dataConfidence": "high",
  "cachedAt": "2026-04-30T19:28:14.317Z"
}