{
  "fullName": "THOMAS SCRUBB",
  "sourceUrl": "https://basketball.eurobasket.com/player/Thomas-Scrubb/187905",
  "height": "6'6'",
  "college": "University National Team",
  "currentTeam": "Tenerife",
  "careerHistory": [
    {
      "year": "10-11",
      "team": "Carleton",
      "league": "USPO"
    },
    {
      "year": "11-12",
      "team": "Carleton",
      "league": "USPO"
    },
    {
      "year": "12-13",
      "team": "Carleton",
      "league": "USPO"
    },
    {
      "year": "13-14",
      "team": "Carleton",
      "league": "USPO"
    },
    {
      "year": "14-15",
      "team": "Carleton",
      "league": "USPO"
    },
    {
      "year": "15-16",
      "team": "Kataja",
      "league": "FEL-1"
    },
    {
      "year": "15-16",
      "team": "Kataja",
      "league": "FIN-1"
    },
    {
      "year": "16-17",
      "team": "Giessen 46ers",
      "league": "GER-1"
    },
    {
      "year": "17-18",
      "team": "Scandone AV",
      "league": "BCL-1"
    },
    {
      "year": "17-18",
      "team": "Scandone AV",
      "league": "FEL-1"
    },
    {
      "year": "17-18",
      "team": "Scandone AV",
      "league": "ITA-1"
    },
    {
      "year": "18-19",
      "team": "OpenjobMetis",
      "league": "FEL-1"
    },
    {
      "year": "18-19",
      "team": "OpenjobMetis",
      "league": "ITA-1"
    },
    {
      "year": "19-20",
      "team": "Strasbourg",
      "league": "FRA-1"
    },
    {
      "year": "19-20",
      "team": "Strasbourg",
      "league": "BCL-1"
    },
    {
      "year": "2020",
      "team": "Ottawa",
      "league": "CEBL"
    },
    {
      "year": "20-21",
      "team": "JL Bourg",
      "league": "Eurocup-1"
    },
    {
      "year": "20-21",
      "team": "JL Bourg",
      "league": "FRA-1"
    },
    {
      "year": "2021",
      "team": "Niagara",
      "league": "CEBL"
    },
    {
      "year": "21-22",
      "team": "Monbus OB",
      "league": "ESP-1"
    },
    {
      "year": "2022",
      "team": "Ottawa",
      "league": "CEBL"
    },
    {
      "year": "22-23",
      "team": "Monbus OB",
      "league": "ESP-1"
    },
    {
      "year": "2023",
      "team": "Ottawa",
      "league": "CEBL"
    },
    {
      "year": "23-24",
      "team": "Monbus OB",
      "league": "BCL-1"
    },
    {
      "year": "23-24",
      "team": "Monbus OB",
      "league": "ESP-1"
    },
    {
      "year": "24-25",
      "team": "Laguna Tenerife",
      "league": "BCL-1"
    },
    {
      "year": "24-25",
      "team": "Laguna Tenerife",
      "league": "ESP-1"
    },
    {
      "year": "25-26",
      "team": "Tenerife",
      "league": "BCL-1"
    },
    {
      "year": "25-26",
      "team": "Tenerife",
      "league": "ESP-1"
    }
  ],
  "_lastVerified": "2026-05-01T03:21:12.746Z",
  "_sources": [
    "eurobasket.com"
  ],
  "_dataConfidence": "high",
  "cachedAt": "2026-04-30T19:54:21.702Z",
  "birthdate": "September 26 1991",
  "birthCity": "Vancouver"
}